{"cameraMode":{"drawMode":0,"name":"Shaded","section":"Shading Mode"},"sceneLighting":true,"audioPlay":false,"sceneViewState":{"m_AlwaysRefresh":false,"showFog":true,"showSkybox":true,"showFlares":true,"showImageEffects":true,"showParticleSystems":true,"showVisualEffectGraphs":true,"m_FxEnabled":true},"in2DMode":false,"pivot":{"x":-12.960793495178223,"y":3.502298593521118,"z":0.3098032474517822},"rotation":{"x":-0.3900982439517975,"y":-0.6096920371055603,"z":0.47641056776046755,"w":-0.4991852045059204},"size":1.205918788909912,"orthographic":false}